tilelog/__init__.py
tilelog/aggregate.py
tilelog/app.py
tilelog/constants.py
tilelog/country.py
tilelog/host.py
tilelog/location.py
tilelog/minimise.py
tilelog-1.8.0.dist-info/METADATA
tilelog-1.8.0.dist-info/WHEEL
tilelog-1.8.0.dist-info/entry_points.txt
tilelog-1.8.0.dist-info/licenses/LICENSE
tilelog-1.8.0.dist-info/RECORD
