Metadata-Version: 2.4
Name: tilelog
Version: 1.8.0
Summary: Process OpenStreetMap tile logs
License-Expression: GPL-3.0-or-later
License-File: LICENSE
Classifier: Development Status :: 5 - Production/Stable
Classifier: Environment :: Console
Classifier: License :: OSI Approved :: GNU General Public License v3 or later (GPLv3+)
Classifier: Operating System :: POSIX :: Linux
Classifier: Programming Language :: Python :: 3
Requires-Python: <4,>=3.10
Requires-Dist: click
Requires-Dist: publicsuffixlist
Requires-Dist: pyathena
Requires-Dist: pyathena[pandas]
